<?xml version="1.0" encoding="UTF-8" ?>
<tc:clients xmlns:tc="https://www.example.com" >
    <client>
        <lastName>Иванов</lastName>
        <firstName>Иван</firstName>
        <patronymicName>Иванович</patronymicName>
        <birthDate>1990-05-12</birthDate>
        <passportSeries>MP</passportSeries>
        <passportNumber>2574120</passportNumber>
        <passportPersonalNumber>5120590A025PB5</passportPersonalNumber>
        <city>
            <cityCode>MSQ</cityCode>
            <cityName>Минск</cityName>
        </city>
        <residenceAddress>ул. Платонова, 32-15</residenceAddress>
        <mobilePhone>+375296305412</mobilePhone>
        <email>ivanovivan@gmail.com</email>
        <employed>true</employed>
        <workPosition>Инженер-программист</workPosition>
        <registrationAddress>ул. Платонова, 32-15</registrationAddress>
        <country>
            <countryCode>BY</countryCode>
            <countryName>Беларусь</countryName>
        </country>
    </client>
    <client>
        <lastName>Петров</lastName>
        <firstName>Петр</firstName>
        <patronymicName>Петрович</patronymicName>
        <birthDate>1996-11-04</birthDate>
        <passportSeries>MP</passportSeries>
        <passportNumber>5102412</passportNumber>
        <passportPersonalNumber>5041196A014PB5</passportPersonalNumber>
        <city>
            <cityCode>BQT</cityCode>
            <cityName>Брест</cityName>
        </city>
        <residenceAddress>ул. Купалы, 24</residenceAddress>
        <mobilePhone>+375447205878</mobilePhone>
        <email>petrov@mail.ru</email>
        <employed>true</employed>
        <workPosition>Старший преподаватель</workPosition>
        <registrationAddress>ул. Купалы, 24</registrationAddress>
        <country>
            <countryCode>BY</countryCode>
            <countryName>Беларусь</countryName>
        </country>
    </client>
</tc:clients>